<?xml version="1.0" encoding="UTF-8"?>
<!DOCTYPE hibernate-mapping PUBLIC "-//Hibernate/Hibernate Mapping DTD 3.0//EN" "http://hibernate.sourceforge.net/hibernate-mapping-3.0.dtd">
<hibernate-mapping>
  <class name="com.whwr.domain.ck.CkRkd" table="ckrkd">
    <id name="id" type="java.lang.Integer">
      <column name="id"/>
      <generator class="increment"/>
    </id>
    <property name="lsh" type="java.lang.String">
      <column name="lsh"/>
    </property>
    <property name="cangku_id" type="java.lang.Integer">
      <column name="cangku_id"/>
    </property>
    <property name="cangku_mc" type="java.lang.String">
      <column name="cangku_mc"/>
    </property>
    <property name="a01_id" type="java.lang.Integer">
      <column name="a01_id"/>
    </property>
    <property name="l_zsl" type="java.lang.Double">
      <column name="l_zsl"/>
    </property>
    <property name="l_zje" type="java.lang.Double">
      <column name="l_zje"/>
    </property>
    <property name="l_jhr" type="java.lang.String">
      <column name="l_jhr"/>
    </property>
    <property name="l_spr" type="java.lang.String">
      <column name="l_spr"/>
    </property>
    <property name="l_date" type="java.util.Date">
      <column name="l_date"/>
    </property>
    <property name="l_state" type="java.lang.String">
      <column name="l_state"/>
    </property>
    <property name="l_bz" type="java.lang.String">
      <column name="l_bz"/>
    </property>
  </class>
</hibernate-mapping>
